django_oidc_provider-0.9.0.dist-info/licenses/LICENSE
oidc_provider/__init__.py
oidc_provider/admin.py
oidc_provider/apps.py
oidc_provider/compat.py
oidc_provider/middleware.py
oidc_provider/models.py
oidc_provider/settings.py
oidc_provider/signals.py
oidc_provider/urls.py
oidc_provider/version.py
oidc_provider/views.py
oidc_provider/lib/__init__.py
oidc_provider/lib/claims.py
oidc_provider/lib/errors.py
oidc_provider/lib/endpoints/__init__.py
oidc_provider/lib/endpoints/authorize.py
oidc_provider/lib/endpoints/introspection.py
oidc_provider/lib/endpoints/token.py
oidc_provider/lib/utils/__init__.py
oidc_provider/lib/utils/authorize.py
oidc_provider/lib/utils/common.py
oidc_provider/lib/utils/oauth2.py
oidc_provider/lib/utils/sanitization.py
oidc_provider/lib/utils/token.py
oidc_provider/locale/es/LC_MESSAGES/django.mo
oidc_provider/locale/es/LC_MESSAGES/django.po
oidc_provider/locale/fr/LC_MESSAGES/django.mo
oidc_provider/locale/fr/LC_MESSAGES/django.po
oidc_provider/locale/pl/LC_MESSAGES/django.mo
oidc_provider/locale/pl/LC_MESSAGES/django.po
oidc_provider/locale/ru/LC_MESSAGES/django.mo
oidc_provider/locale/ru/LC_MESSAGES/django.po
oidc_provider/locale/zh_Hans/LC_MESSAGES/django.mo
oidc_provider/locale/zh_Hans/LC_MESSAGES/django.po
oidc_provider/management/__init__.py
oidc_provider/management/commands/__init__.py
oidc_provider/management/commands/creatersakey.py
oidc_provider/migrations/0001_initial.py
oidc_provider/migrations/0002_userconsent.py
oidc_provider/migrations/0003_code_nonce.py
oidc_provider/migrations/0004_remove_userinfo.py
oidc_provider/migrations/0005_token_refresh_token.py
oidc_provider/migrations/0006_unique_user_client.py
oidc_provider/migrations/0007_auto_20160111_1844.py
oidc_provider/migrations/0008_rsakey.py
oidc_provider/migrations/0009_auto_20160202_1945.py
oidc_provider/migrations/0010_code_is_authentication.py
oidc_provider/migrations/0011_client_client_type.py
oidc_provider/migrations/0012_auto_20160405_2041.py
oidc_provider/migrations/0013_auto_20160407_1912.py
django_oidc_provider-0.9.0.dist-info/METADATA
django_oidc_provider-0.9.0.dist-info/WHEEL
django_oidc_provider-0.9.0.dist-info/top_level.txt
django_oidc_provider-0.9.0.dist-info/RECORD
